pycounts_aw/__init__.py
pycounts_aw/plotting_aw.py
pycounts_aw/pycounts_aw.py
pycounts_aw-0.1.0.dist-info/LICENSE
pycounts_aw-0.1.0.dist-info/METADATA
pycounts_aw-0.1.0.dist-info/WHEEL
pycounts_aw-0.1.0.dist-info/RECORD
